c_sum_py/c_sum_py.py
c_sum_py/demo.py
my_package_fiveplus/__init__.py
my_package_fiveplus/sub.py
my_package_fiveplus/sum.py
my_package_fiveplus-0.4.0.dist-info/METADATA
my_package_fiveplus-0.4.0.dist-info/WHEEL
my_package_fiveplus-0.4.0.dist-info/top_level.txt
my_package_fiveplus-0.4.0.dist-info/RECORD
