Metadata-Version: 2.1
Name: my-package-fiveplus
Version: 0.4.0
Summary: 姬小野的pypi测试项目.
Home-page: https://github.com/JameyWoo
Author: Fiveplus
Author-email: 2622075127@qq.com
License: MIT
Platform: UNKNOWN
Classifier: License :: OSI Approved :: MIT License
Classifier: Programming Language :: Python
Classifier: Programming Language :: Python :: 3
Classifier: Programming Language :: Python :: 3.6
Classifier: Programming Language :: Python :: Implementation :: CPython
Classifier: Programming Language :: Python :: Implementation :: PyPy
Requires-Python: >=3.6.0
